QuickJSON/__init__.py
QuickJSON_nicky-0.0.4.dist-info/METADATA
QuickJSON_nicky-0.0.4.dist-info/WHEEL
QuickJSON_nicky-0.0.4.dist-info/top_level.txt
QuickJSON_nicky-0.0.4.dist-info/RECORD
