Metadata-Version: 2.1
Name: QuickJSON-nicky
Version: 0.0.4
Summary: removing all the open(file, 'w') hassle from saving a simple json
Home-page: https://github.com/Nicky5/QuickJSON
Author: nicky
Author-email: nickychan3232@gmail.com
Project-URL: Bug Tracker, https://github.com/Nicky5/QuickJSON/issues
Classifier: Programming Language :: Python :: 3
Classifier: Operating System :: OS Independent
Requires-Python: >=3.6
